new_src/uart/uart_tx_debug.v
module uart_tx_debug #(
    parameter CLKS_PER_BIT = 5208
)(
    input wire       clk,
    input wire       rst_n,
    input wire       tx_start,
    input wire [7:0] tx_data,
    output reg       tx_serial,
    output reg       busy,
    // --- NUEVA SEÑAL PARA DEBUG ---
    output reg       o_baud_tick // Pulso al final de cada bit
);

    localparam IDLE  = 2'b00;
    localparam START = 2'b01;
    localparam DATA  = 2'b10;
    localparam STOP  = 2'b11;

    reg [1:0]  state;
    reg [12:0] clk_count;
    reg [2:0]  bit_index;
    reg [7:0]  data_temp;

    always @(posedge clk or negedge rst_n) begin
        if (!rst_n) begin
            state       <= IDLE;
            tx_serial   <= 1'b1;
            busy        <= 1'b0;
            clk_count   <= 0;
            bit_index   <= 0;
            data_temp   <= 0;
            o_baud_tick <= 1'b0; // Reset del tick
        end else begin
            // Por defecto el tick está en bajo, solo sube un ciclo al final del conteo
            o_baud_tick <= 1'b0; 

            case (state)
                IDLE: begin
                    tx_serial <= 1'b1;
                    busy      <= 1'b0;
                    clk_count <= 0;
                    bit_index <= 0;
                    
                    if (tx_start == 1'b1) begin
                        data_temp <= tx_data;
                        busy      <= 1'b1;
                        state     <= START;
                    end
                end

                START: begin
                    tx_serial <= 1'b0;
                    
                    if (clk_count < CLKS_PER_BIT - 1) begin
                        clk_count <= clk_count + 1;
                    end else begin
                        clk_count   <= 0;
                        o_baud_tick <= 1'b1; // <--- ¡PULSO DE DEBUG!
                        state       <= DATA;
                    end
                end

                DATA: begin
                    tx_serial <= data_temp[bit_index];
                    
                    if (clk_count < CLKS_PER_BIT - 1) begin
                        clk_count <= clk_count + 1;
                    end else begin
                        clk_count   <= 0;
                        o_baud_tick <= 1'b1; // <--- ¡PULSO DE DEBUG!
                        
                        if (bit_index < 7) begin
                            bit_index <= bit_index + 1;
                        end else begin
                            bit_index <= 0;
                            state     <= STOP;
                        end
                    end
                end

                STOP: begin
                    tx_serial <= 1'b1;
                    
                    if (clk_count < CLKS_PER_BIT - 1) begin
                        clk_count <= clk_count + 1;
                    end else begin
                        clk_count   <= 0;
                        o_baud_tick <= 1'b1; // <--- ¡PULSO DE DEBUG!
                        busy        <= 1'b0;
                        state       <= IDLE;
                    end
                end
                
                default: state <= IDLE;
            endcase
        end
    end
endmodule

new_src/uart/tb_uart_tx.v
`timescale 1ns / 1ps
`include "uart_tx_debug.v"
module tb_uart_debug;

    reg clk;
    reg rst_n;
    reg tx_start;
    reg [7:0] tx_data;

    wire tx_serial;
    wire busy;
    wire o_baud_tick; // Cable para ver el tick

    // Usamos divisor pequeño para simulación visual rápida
    localparam CLKS_PER_BIT = 4; 
    localparam CLK_PERIOD = 20;

    uart_tx_debug #(.CLKS_PER_BIT(CLKS_PER_BIT)) uut (
        .clk(clk),
        .rst_n(rst_n),
        .tx_start(tx_start),
        .tx_data(tx_data),
        .tx_serial(tx_serial),
        .busy(busy),
        .o_baud_tick(o_baud_tick) // Conexión nueva
    );

    always #(CLK_PERIOD/2) clk = ~clk;

    initial begin
        $dumpfile("uart_debug.vcd");
        $dumpvars(0, tb_uart_debug);

        clk = 0; rst_n = 0; tx_start = 0; tx_data = 0;
        
        #100;
        rst_n = 1;
        #40;

        // Enviar letra 'A' (0x41 = 01000001) -> LSB primero: 10000010
        tx_data = 8'h41; 
        tx_start = 1;
        #20;
        tx_start = 0;

        wait(busy == 0);
        #100;
        $finish;
    end
endmodule

uart/uart_debug.vcd
$date
	Tue Dec 02 20:38:26 2025
$end
$version
	Icarus Verilog
$end
$timescale
	1ps
$end
$scope module tb_uart_debug $end
$var wire 1 ! tx_serial $end
$var wire 1 " o_baud_tick $end
$var wire 1 # busy $end
$var parameter 32 $ CLKS_PER_BIT $end
$var parameter 32 % CLK_PERIOD $end
$var reg 1 & clk $end
$var reg 1 ' rst_n $end
$var reg 8 ( tx_data [7:0] $end
$var reg 1 ) tx_start $end
$scope module uut $end
$var wire 1 & clk $end
$var wire 1 ' rst_n $end
$var wire 8 * tx_data [7:0] $end
$var wire 1 ) tx_start $end
$var parameter 32 + CLKS_PER_BIT $end
$var parameter 2 , DATA $end
$var parameter 2 - IDLE $end
$var parameter 2 . START $end
$var parameter 2 / STOP $end
$var reg 3 0 bit_index [2:0] $end
$var reg 1 # busy $end
$var reg 13 1 clk_count [12:0] $end
$var reg 8 2 data_temp [7:0] $end
$var reg 1 " o_baud_tick $end
$var reg 2 3 state [1:0] $end
$var reg 1 ! tx_serial $end
$upscope $end
$upscope $end
$enddefinitions $end
$comment Show the parameter values. $end
$dumpall
b11 /
b1 .
b0 -
b10 ,
b100 +
b10100 %
b100 $
$end
#0
$dumpvars
b0 3
b0 2
b0 1
b0 0
b0 *
0)
b0 (
0'
0&
0#
0"
1!
$end
#10000
1&
#20000
0&
#30000
1&
#40000
0&
#50000
1&
#60000
0&
#70000
1&
#80000
0&
#90000
1&
#100000
0&
1'
#110000
1&
#120000
0&
#130000
1&
#140000
0&
1)
b1000001 (
b1000001 *
#150000
b1 3
1#
b1000001 2
1&
#160000
0&
0)
#170000
b1 1
0!
1&
#180000
0&
#190000
b10 1
1&
#200000
0&
#210000
b11 1
1&
#220000
0&
#230000
b10 3
1"
b0 1
1&
#240000
0&
#250000
b1 1
1!
0"
1&
#260000
0&
#270000
b10 1
1&
#280000
0&
#290000
b11 1
1&
#300000
0&
#310000
b1 0
1"
b0 1
1&
#320000
0&
#330000
b1 1
0!
0"
1&
#340000
0&
#350000
b10 1
1&
#360000
0&
#370000
b11 1
1&
#380000
0&
#390000
b10 0
1"
b0 1
1&
#400000
0&
#410000
b1 1
0"
1&
#420000
0&
#430000
b10 1
1&
#440000
0&
#450000
b11 1
1&
#460000
0&
#470000
b11 0
1"
b0 1
1&
#480000
0&
#490000
b1 1
0"
1&
#500000
0&
#510000
b10 1
1&
#520000
0&
#530000
b11 1
1&
#540000
0&
#550000
b100 0
1"
b0 1
1&
#560000
0&
#570000
b1 1
0"
1&
#580000
0&
#590000
b10 1
1&
#600000
0&
#610000
b11 1
1&
#620000
0&
#630000
b101 0
1"
b0 1
1&
#640000
0&
#650000
b1 1
0"
1&
#660000
0&
#670000
b10 1
1&
#680000
0&
#690000
b11 1
1&
#700000
0&
#710000
b110 0
1"
b0 1
1&
#720000
0&
#730000
b1 1
1!
0"
1&
#740000
0&
#750000
b10 1
1&
#760000
0&
#770000
b11 1
1&
#780000
0&
#790000
b111 0
1"
b0 1
1&
#800000
0&
#810000
b1 1
0!
0"
1&
#820000
0&
#830000
b10 1
1&
#840000
0&
#850000
b11 1
1&
#860000
0&
#870000
b11 3
b0 0
1"
b0 1
1&
#880000
0&
#890000
b1 1
1!
0"
1&
#900000
0&
#910000
b10 1
1&
#920000
0&
#930000
b11 1
1&
#940000
0&
#950000
b0 3
0#
1"
b0 1
1&
#960000
0&
#970000
0"
1&
